regolo/__init__.py
regolo/cli.py
regolo/client/__init__.py
regolo/client/regolo_client.py
regolo/instance/__init__.py
regolo/instance/regolo_instance.py
regolo/instance/structures/__init__.py
regolo/instance/structures/conversation_model.py
regolo/keys/__init__.py
regolo/keys/keys.py
regolo/models/__init__.py
regolo/models/models.py
regolo-1.9.1.dist-info/licenses/LICENSE
regolo-1.9.1.dist-info/METADATA
regolo-1.9.1.dist-info/WHEEL
regolo-1.9.1.dist-info/entry_points.txt
regolo-1.9.1.dist-info/top_level.txt
regolo-1.9.1.dist-info/RECORD
