Metadata-Version: 2.4
Name: regolo
Version: 1.9.1
Summary: Simple client to interact with regolo.ai
Author-email: "regolo.ai" <dev@regolo.ai>
License-Expression: MIT
Project-URL: Homepage, https://github.com/regolo-ai/python-client
Keywords: chat,llm,regolo
Classifier: Programming Language :: Python
Classifier: Programming Language :: Python :: 3 :: Only
Classifier: Programming Language :: Python :: 3.12
Requires-Python: >=3.12
License-File: LICENSE
Requires-Dist: click==8.1.8
Requires-Dist: httpx~=0.28.1
Requires-Dist: json-repair~=0.35.0
Requires-Dist: pillow~=11.1.0
Requires-Dist: pydantic~=2.10.6
Requires-Dist: python-dotenv
Requires-Dist: requests
Provides-Extra: dev
Requires-Dist: bumpver; extra == "dev"
Requires-Dist: pip-tools; extra == "dev"
Requires-Dist: pre-commit; extra == "dev"
Requires-Dist: pytest; extra == "dev"
Requires-Dist: python-dotenv; extra == "dev"
Provides-Extra: imgs
Requires-Dist: pillow~=11.1.0; extra == "imgs"
Dynamic: license-file
